graph_rag_example_helpers/__init__.py
graph_rag_example_helpers/env.py
graph_rag_example_helpers/persistent_iteration.py
graph_rag_example_helpers/datasets/__init__.py
graph_rag_example_helpers/datasets/animals/__init__.py
graph_rag_example_helpers/datasets/animals/fetch.py
graph_rag_example_helpers/datasets/astrapy/__init__.py
graph_rag_example_helpers/datasets/astrapy/fetch.py
graph_rag_example_helpers/datasets/wikimultihop/__init__.py
graph_rag_example_helpers/datasets/wikimultihop/load.py
graph_rag_example_helpers/examples/__init__.py
graph_rag_example_helpers/examples/code_generation/__init__.py
graph_rag_example_helpers/examples/code_generation/converter.py
graph_rag_example_helpers/examples/code_generation/format.py
graph_rag_example_helpers-0.8.0.dist-info/METADATA
graph_rag_example_helpers-0.8.0.dist-info/WHEEL
graph_rag_example_helpers-0.8.0.dist-info/licenses/LICENSE
graph_rag_example_helpers-0.8.0.dist-info/RECORD
